MANIFEST.in
readme.MD
setup.py
TikTokResearchApi.egg-info/PKG-INFO
TikTokResearchApi.egg-info/SOURCES.txt
TikTokResearchApi.egg-info/dependency_links.txt
TikTokResearchApi.egg-info/requires.txt
TikTokResearchApi.egg-info/top_level.txt
tiktok_research_api/__init__.py
tiktok_research_api/api.py
tiktok_research_api/criteria.py
tiktok_research_api/errors.py
tiktok_research_api/query.py
tiktok_research_api/query_user_followers_request.py
tiktok_research_api/query_user_following_request.py
tiktok_research_api/query_user_info_request.py
tiktok_research_api/query_user_liked_videos_request.py
tiktok_research_api/query_user_pinned_videos_request.py
tiktok_research_api/query_user_reposted_video_request.py
tiktok_research_api/query_video_comments_request.py
tiktok_research_api/query_video_request.py
tiktok_research_api/reposted_video_request.py