Metadata-Version: 2.1
Name: TikTokResearchApi
Version: 1.0.4
Summary: A Python package for interacting with the TikTok Research API
Home-page: 
Author-email: 
Requires-Python: >=3.6
Requires-Dist: requests>=2.20.0
